advent_of_code_py/__init__.py
advent_of_code_py/cache_file.py
advent_of_code_py/cli.py
advent_of_code_py/config_file.py
advent_of_code_py/initializer.py
advent_of_code_py/puzzle.py
advent_of_code_py/runner.py
advent_of_code_py/server_action.py
advent_of_code_py/utils.py
advent_of_code_py-0.4.0.dist-info/LICENSE
advent_of_code_py-0.4.0.dist-info/METADATA
advent_of_code_py-0.4.0.dist-info/WHEEL
advent_of_code_py-0.4.0.dist-info/entry_points.txt
advent_of_code_py-0.4.0.dist-info/RECORD
