Metadata-Version: 2.1
Name: advent-of-code-py
Version: 0.4.0
Summary: Advent of Code helper CLI and library
Home-page: https://github.com/iamsauravsharma/advent-of-code-py
License: MIT
Keywords: advent-of-code,aoc,aocpy,advent of code
Author: Saurav Sharma
Author-email: appdroiddeveloper@gmail.com
Requires-Python: >=3.7,<4.0
Classifier: Development Status :: 4 - Beta
Classifier: Intended Audience :: Developers
Classifier: License :: OSI Approved :: MIT License
Classifier: Programming Language :: Python :: 3
Classifier: Programming Language :: Python :: 3.7
Classifier: Programming Language :: Python :: 3.8
Classifier: Programming Language :: Python :: 3.9
Classifier: Programming Language :: Python :: 3.10
Classifier: Programming Language :: Python :: 3.11
Classifier: Programming Language :: Python :: 3
Classifier: Topic :: Games/Entertainment :: Puzzle Games
Classifier: Topic :: Software Development :: Libraries
Requires-Dist: click (>=8.0,<9.0)
Requires-Dist: platformdirs (>=3.0.0,<4.0.0)
Requires-Dist: pytz (>=2022.7.1,<2023.0.0)
Requires-Dist: requests (>=2.22.0,<3.0.0)
Project-URL: Repository, https://github.com/iamsauravsharma/advent-of-code-py
